netonix_api.py
python_netonix_api-0.2.1.dist-info/LICENSE
python_netonix_api-0.2.1.dist-info/METADATA
python_netonix_api-0.2.1.dist-info/WHEEL
python_netonix_api-0.2.1.dist-info/top_level.txt
python_netonix_api-0.2.1.dist-info/RECORD
