Metadata-Version: 2.1
Name: python-netonix-api
Version: 0.2.1
Summary: Python class to access Netonix WISP Switch WebAPI
Home-page: https://github.com/shrank/python_netonix_api
Author: shrank
Author-email: shrank <info@murxs.ch>
License: This is free and unencumbered software released into the public domain.
Project-URL: Homepage, https://github.com/shrank/python_netonix_api
Keywords: network,automation,netonix
Classifier: Programming Language :: Python :: 3
Classifier: Operating System :: OS Independent
Requires-Python: >=3.0
License-File: LICENSE
Requires-Dist: requests
Provides-Extra: dev
Requires-Dist: deepdiff ; extra == 'dev'
Requires-Dist: getpass ; extra == 'dev'
Requires-Dist: urllib3 ; extra == 'dev'
